pytest_mypy_runner/__init__.py
pytest_mypy_runner/mypy_test_runner.py
pytest_mypy_runner/py.typed
pytest_mypy_runner-1.0.0.dist-info/LICENSE
pytest_mypy_runner-1.0.0.dist-info/METADATA
pytest_mypy_runner-1.0.0.dist-info/WHEEL
pytest_mypy_runner-1.0.0.dist-info/RECORD
